README.txt
setup.py
froggie/__init__.py
froggie/conf.py
froggie/download_atomhopper.py
froggie/maven.py
froggie/pathutil.py
froggie.egg-info/PKG-INFO
froggie.egg-info/SOURCES.txt
froggie.egg-info/dependency_links.txt
froggie.egg-info/entry_points.txt
froggie.egg-info/requires.txt
froggie.egg-info/top_level.txt