Metadata-Version: 1.1
Name: froggie
Version: 0.1.1
Summary: Setup scripts for installing atom hopper on a server for automated testing
Home-page: https://github.com/richard-sartor/froggie
Author: Richard Sartor
Author-email: richard.sartor@rackspace.com
License: MIT License
Platform: UNKNOWN
Classifier: Development Status :: 3 - Alpha
Classifier: Intended Audience :: Developers
Classifier: Natural Language :: English
Classifier: License :: OSI Approved :: MIT License
Classifier: Programming Language :: Python
Classifier: Programming Language :: Python :: 2.7
